setup.py
payer_api/__init__.py
payer_api/order.py
payer_api/postapi.py
payer_api/xml.py
python_payer_api.egg-info/PKG-INFO
python_payer_api.egg-info/SOURCES.txt
python_payer_api.egg-info/dependency_links.txt
python_payer_api.egg-info/requires.txt
python_payer_api.egg-info/top_level.txt