Metadata-Version: 1.1
Name: python-payer-api
Version: 0.1.0
Summary: Python package for interacting with the Payer payments API (http://www.payer.se).
Home-page: https://github.com/dessibelle/python-payer-api
Author: Simon Fransson
Author-email: simon@dessibelle.se
License: MIT
Download-URL: https://github.com/dessibelle/python-payer-api/archive/0.1.0.tar.gz
Platform: UNKNOWN
Classifier: Intended Audience :: Developers
Classifier: License :: OSI Approved :: MIT License
Classifier: Operating System :: OS Independent
Classifier: Topic :: Software Development
